crossabc/__init__.py
crossabc/crossabc.py
crossabc-0.1.7.dist-info/entry_points.txt
crossabc-0.1.7.dist-info/LICENSE
crossabc-0.1.7.dist-info/WHEEL
crossabc-0.1.7.dist-info/METADATA
crossabc-0.1.7.dist-info/RECORD
