Metadata-Version: 2.1
Name: crossabc
Version: 0.1.7
Summary: Easily CrossABC analyzer
Home-page: https://github.com/hrt0809/crossabc
License: MIT
Keywords: data-analysis,pareto-analysis,ABC-analysis
Author: Hiroto Ueda
Author-email: hrt.ueda0809@gmail.com
Maintainer: Hiroto Ueda
Maintainer-email: hrt.ueda0809@gmail.com
Requires-Python: >=3.7.1
Classifier: Development Status :: 4 - Beta
Classifier: Intended Audience :: Science/Research
Classifier: License :: OSI Approved :: MIT License
Classifier: Programming Language :: Python :: 3
Classifier: Programming Language :: Python :: 3.8
Classifier: Programming Language :: Python :: 3.9
Classifier: Programming Language :: Python :: 3.10
Classifier: Programming Language :: Python :: 3.11
Classifier: Topic :: Scientific/Engineering
Classifier: Topic :: Scientific/Engineering :: Information Analysis
Requires-Dist: numpy (==1.21.6); python_full_version <= "3.7.15"
Requires-Dist: numpy (==1.23.4); python_version >= "3.8"
Requires-Dist: pandas (==1.3.5); python_full_version <= "3.7.15"
Requires-Dist: pandas (==1.5.1); python_version >= "3.8"
Project-URL: Documentation, https://github.com/hrt0809/crossabc
Project-URL: Repository, https://github.com/hrt0809/crossabc
